{
    "resourceType": "Observation",
    "id": "CML.MONITOR.7766787",
    "meta": {
        "profile": [
            "http://fhir.health.gov.il/StructureDefinition/il-core-observation"
        ]
    },
    "identifier": [
        {
            "system": "http://fhir.b-zion.health.gov.il/identifier/cml-manual-monitor",
            "value": "7766787"
        }
    ],
    "status": "final",
    "category": [
        {
            "coding": [
                {
                    "system": "http://fhir.dgmc.health.gov.il/cs/cml-parameters-category",
                    "code": "clinical-monitor",
                    "display": "Clinical Monitor"
                }
            ]
        }
    ],
    "code": {
        "coding": [
            {
                "system": "http://loinc.org",
                "code": "2339-0",
                "display": "Glucose [Mass/volume] in Blood"
            },
            {
                "system": "http://fhir.dgmc.health.gov.il/cs/cml-parameters",
                "code": "14",
                "display": "סוכר בדם"
            }
        ]
    },
    "subject": {
        "reference": "Patient/PAT.2151512"
    },
    "encounter": {
        "reference": "Encounter/CML.1886454"
    },
    "effectiveDateTime": "2025-08-14T14:10:00+03:00",
    "issued": "2025-08-14T14:13:26.903+03:00",
    "performer": [
        {
            "reference": "Practitioner/CML.10381"
        }
    ],
    "valueQuantity": {
        "value": 220.0,
        "unit": "milligram per deciliter",
        "system": "http://unitsofmeasure.org",
        "code": "mg/dL"
    },
    "referenceRange": [
        {
            "low": {
                "value": 40.0
            },
            "high": {
                "value": 500.0
            }
        }
    ],
    "component": [
        {
            "code": {
                "coding": [
                    {
                        "system": "http://snomed.info/sct",
                        "code": "103333000",
                        "display": "Has timing"
                    }
                ]
            },
            "valueCodeableConcept": {
                "coding": [
                    {
                        "system": "http://snomed.info/sct",
                        "code": "307165006",
                        "display": "Before meal"
                    },
                    {
                        "system": "http://fhir.b-zion.health.gov.il/CodeSystem/cml-monitor-combo",
                        "code": "2",
                        "display": "לפני האוכל"
                    }
                ]
            }
        }
    ]
}